gemini_live_avatar/__init__.py
gemini_live_avatar/api.py
gemini_live_avatar/app.py
gemini_live_avatar/cli.py
gemini_live_avatar/config.py
gemini_live_avatar/mcp_server.py
gemini_live_avatar/session.py
gemini_live_avatar/web.py
gemini_live_avatar/site/background.png
gemini_live_avatar/site/index.html
gemini_live_avatar/site/vite.svg
gemini_live_avatar-0.1.6.dist-info/METADATA
gemini_live_avatar-0.1.6.dist-info/WHEEL
gemini_live_avatar-0.1.6.dist-info/entry_points.txt
gemini_live_avatar-0.1.6.dist-info/RECORD
