Metadata-Version: 2.4
Name: gemini-live-avatar
Version: 0.1.6
Summary: Create a live avatar using Gemini and FastAPI
Author-email: haruiz <henryruiz22@gmail.com>
Requires-Python: >=3.11
Requires-Dist: fastapi[standard]>=0.115.12
Requires-Dist: google-genai>=1.16.1
Requires-Dist: pillow>=11.2.1
Requires-Dist: python-dotenv>=1.1.0
Requires-Dist: rich>=14.0.0
Requires-Dist: typer>=0.16.0
Requires-Dist: uvicorn>=0.34.2
Provides-Extra: mcp-demo
Requires-Dist: fastapi-mcp>=0.3.4; extra == 'mcp-demo'
Requires-Dist: mcp[cli]>=1.9.2; extra == 'mcp-demo'
